topsis_mrinank_102303235/__init__.py
topsis_mrinank_102303235/cli.py
topsis_mrinank_102303235-0.0.1.dist-info/licenses/LICENSE
topsis_mrinank_102303235-0.0.1.dist-info/METADATA
topsis_mrinank_102303235-0.0.1.dist-info/WHEEL
topsis_mrinank_102303235-0.0.1.dist-info/entry_points.txt
topsis_mrinank_102303235-0.0.1.dist-info/top_level.txt
topsis_mrinank_102303235-0.0.1.dist-info/RECORD
