Metadata-Version: 2.4
Name: topsis_mrinank_102303235
Version: 0.0.1
Summary: TOPSIS CLI tool
Author: Mrinank
Classifier: Programming Language :: Python :: 3
Requires-Python: >=3.8
License-File: LICENSE
Requires-Dist: pandas
Requires-Dist: numpy
Dynamic: author
Dynamic: classifier
Dynamic: description
Dynamic: description-content-type
Dynamic: license-file
Dynamic: requires-dist
Dynamic: requires-python
Dynamic: summary
